{
  "slug": "addo-spar",
  "plant_name": "Addo Spar Smart Logger",
  "station_code": "NE=51009860",
  "date": "2026-06-27",
  "total_kwh": 692.28,
  "day_power": 692.28,
  "month_power": 16892.45,
  "total_power": 781735.92,
  "hourly_pv": [
    0.0,
    0.0,
    0.0,
    0.0,
    0.0,
    0.0,
    0.0,
    3.57,
    26.82,
    61.23,
    93.84,
    102.73,
    123.88,
    116.26,
    90.99,
    52.41,
    20.1,
    0.44,
    0.0,
    0.0,
    0.0,
    0.0,
    0.0,
    0.0
  ],
  "last_hour": 17,
  "fetched_at": "2026-06-27T17:40:04.722178"
}